{
  "main": {
    "id": "8295fc0dd76b533d",
    "type": "split",
    "children": [
      {
        "id": "c92e141133f5f957",
        "type": "tabs",
        "children": [
          {
            "id": "5f79af7793597e53",
            "type": "leaf",
            "state": {
              "type": "markdown",
              "state": {
                "file": "Kotlin/Contract 문법.md",
                "mode": "source",
                "source": false
              }
            }
          }
        ]
      }
    ],
    "direction": "vertical"
  },
  "left": {
    "id": "dc01bd6d5a36bdb8",
    "type": "split",
    "children": [
      {
        "id": "a58dd5d54b0c3ef7",
        "type": "tabs",
        "children": [
          {
            "id": "b4f4809249723ca8",
            "type": "leaf",
            "state": {
              "type": "file-explorer",
              "state": {
                "sortOrder": "alphabetical"
              }
            }
          },
          {
            "id": "5a51fdef9b452ade",
            "type": "leaf",
            "state": {
              "type": "search",
              "state": {
                "query": "",
                "matchingCase": false,
                "explainSearch": false,
                "collapseAll": false,
                "extraContext": false,
                "sortOrder": "alphabetical"
              }
            }
          },
          {
            "id": "3c825e7cad1a2c89",
            "type": "leaf",
            "state": {
              "type": "bookmarks",
              "state": {}
            }
          },
          {
            "id": "abf2a948d27a84e9",
            "type": "leaf",
            "state": {
              "type": "mk-file-view",
              "state": {}
            }
          }
        ],
        "currentTab": 3
      }
    ],
    "direction": "horizontal",
    "width": 300
  },
  "right": {
    "id": "f603f03fdfd92c43",
    "type": "split",
    "children": [
      {
        "id": "92cb386332e0286b",
        "type": "tabs",
        "children": [
          {
            "id": "05aa5c1d32fb774e",
            "type": "leaf",
            "state": {
              "type": "backlink",
              "state": {
                "file": "Kotlin/Contract 문법.md",
                "collapseAll": false,
                "extraContext": false,
                "sortOrder": "alphabetical",
                "showSearch": false,
                "searchQuery": "",
                "backlinkCollapsed": false,
                "unlinkedCollapsed": true
              }
            }
          },
          {
            "id": "8b99a199067525ac",
            "type": "leaf",
            "state": {
              "type": "outgoing-link",
              "state": {
                "file": "Kotlin/Contract 문법.md",
                "linksCollapsed": false,
                "unlinkedCollapsed": true
              }
            }
          },
          {
            "id": "06a912348dae60de",
            "type": "leaf",
            "state": {
              "type": "tag",
              "state": {
                "sortOrder": "frequency",
                "useHierarchy": true
              }
            }
          },
          {
            "id": "c10979b597d69c92",
            "type": "leaf",
            "state": {
              "type": "outline",
              "state": {
                "file": "Kotlin/Contract 문법.md"
              }
            }
          }
        ]
      }
    ],
    "direction": "horizontal",
    "width": 300,
    "collapsed": true
  },
  "left-ribbon": {
    "hiddenItems": {
      "switcher:퀵 스위처 열기": false,
      "graph:그래프 뷰 열기": false,
      "canvas:새 캔버스 만들기": false,
      "daily-notes:오늘의 데일리 노트 열기": false,
      "templates:템플릿 삽입": false,
      "command-palette:명령어 팔레트 열기": false
    }
  },
  "active": "5f79af7793597e53",
  "lastOpenFiles": [
    "클린 아키텍처/3. 코드 구성하기.md",
    "Pasted image 20231127210435.png",
    "Pasted image 20231127210231.png",
    "Pasted image 20231127195026.png",
    "클린 아키텍처/2. 의존성 역전하기.md",
    "Pasted image 20231127193307.png",
    "Snipaste_2023-11-27_18-55-44@2x.png",
    "Pasted image 20231127185500.png",
    "Pasted image 20231127183227.png",
    "Pasted image 20231127161116.png",
    "Pasted image 20231127160403.png",
    "클린 아키텍처/1. 계층형 아키텍처.md",
    "클린 아키텍처/Pasted image 20231127154817.png",
    "코테/14888.md",
    "코테/2309.md",
    "Kotlin/Contract 문법.md",
    "Kotlin/Kotlin QueryDSL.md",
    "코테/코테.md",
    "코테",
    "Spring/ArgumentResolver.md",
    "Spaces/Home",
    "Spaces",
    "Excalidraw/Drawing 2023-11-18 18.03.03.excalidraw.md",
    "Kotlin/Test.md",
    "클린 아키텍처/클린 아키텍처.md",
    "클린 아키텍처",
    "Untitled.md",
    "Spring/Spring.md",
    "Spring",
    "Excalidraw",
    "Kotlin",
    "Kotlin QueryDSL.md",
    "kotlin/Kotlin QueryDSL.md",
    "kotlin"
  ]
}